requirements.txt
setup.py
django_site_id_middleware/__init__.py
django_site_id_middleware/middleware.py
django_site_id_middleware.egg-info/PKG-INFO
django_site_id_middleware.egg-info/SOURCES.txt
django_site_id_middleware.egg-info/dependency_links.txt
django_site_id_middleware.egg-info/requires.txt
django_site_id_middleware.egg-info/top_level.txt