Metadata-Version: 2.1
Name: django-site-id-middleware
Version: 2020.7.1
Summary: auto settings.SITE_ID middleware
Home-page: https://github.com/andrewp-as-is/django-site-id-middleware.py
License: Unlicense
Keywords: django site middleware
Platform: UNKNOWN
Classifier: Framework :: Django
Classifier: License :: Public Domain
Classifier: Operating System :: OS Independent
Classifier: Programming Language :: Python :: 3
